chuixue_mcp_yitu_ai/__init__.py
chuixue_mcp_yitu_ai-0.1.11.dist-info/METADATA
chuixue_mcp_yitu_ai-0.1.11.dist-info/WHEEL
chuixue_mcp_yitu_ai-0.1.11.dist-info/entry_points.txt
chuixue_mcp_yitu_ai-0.1.11.dist-info/RECORD
