Metadata-Version: 2.4
Name: chuixue-mcp-yitu-ai
Version: 0.1.11
Summary: Add your description here
Author-email: longchanghua <229162201@qq.com>
Requires-Python: >=3.13
Requires-Dist: mcp[cli]>=1.10.1
Requires-Dist: requests>=2.31.0
